debify.py
setup.py
debify.egg-info/PKG-INFO
debify.egg-info/SOURCES.txt
debify.egg-info/dependency_links.txt
debify.egg-info/requires.txt
debify.egg-info/top_level.txt