Metadata-Version: 1.1
Name: debify
Version: 0.1.3
Summary: pack a set of files into a .deb file with minimal fuss.
Home-page: https://github.com/tengu/debify
Author: karasuyamatengu
Author-email: karasuyamatengu@gmail.com
License: LGPL
Keywords: debian,package
Platform: POSIX
Platform: Windows
Classifier: License :: OSI Approved :: GNU Library or Lesser General Public License (LGPL)
Classifier: Operating System :: POSIX :: Linux
Classifier: Programming Language :: Python
Classifier: Development Status :: 4 - Beta
Classifier: Environment :: Console
Classifier: Intended Audience :: Developers
Classifier: Topic :: Utilities
Classifier: Topic :: Software Development
